glibs_datetime_helpers-1.0.0-py3.10-nspkg.pth
glibs/datetime_helpers.py
glibs_datetime_helpers-1.0.0.dist-info/METADATA
glibs_datetime_helpers-1.0.0.dist-info/WHEEL
glibs_datetime_helpers-1.0.0.dist-info/namespace_packages.txt
glibs_datetime_helpers-1.0.0.dist-info/top_level.txt
glibs_datetime_helpers-1.0.0.dist-info/RECORD
