Metadata-Version: 2.1
Name: glibs-datetime-helpers
Version: 1.0.0
Summary: UNKNOWN
Home-page: UNKNOWN
License: UNKNOWN
Platform: UNKNOWN
Requires-Python: !=3.0.*,!=3.1.*,!=3.2.*,!=3.3.*,!=3.4.*,!=3.5.*,!=3.6.*,!=3.7.*,>=2.7
Requires-Dist: ciso8601 (<2)
Requires-Dist: python-dateutil (<3,>=2.2)
